tracelogdetdiag/__init__.py
tracelogdetdiag/diag/__init__.py
tracelogdetdiag/diag/diag.py
tracelogdetdiag/diag/explicit.py
tracelogdetdiag/diaginv/__init__.py
tracelogdetdiag/diaginv/diaginv.py
tracelogdetdiag/diaginv/explicit.py
tracelogdetdiag/logdet/__init__.py
tracelogdetdiag/logdet/explicit.py
tracelogdetdiag/logdet/stochastic_chebyshev.py
tracelogdetdiag/logdet/util.py
tracelogdetdiag/trace/__init__.py
tracelogdetdiag/trace/hutchinson_trace.py
tracelogdetdiag-0.0.1.dist-info/LICENSE
tracelogdetdiag-0.0.1.dist-info/METADATA
tracelogdetdiag-0.0.1.dist-info/WHEEL
tracelogdetdiag-0.0.1.dist-info/top_level.txt
tracelogdetdiag-0.0.1.dist-info/RECORD
