Metadata-Version: 2.1
Name: tracelogdetdiag
Version: 0.0.1
Summary: Some implementations of randomized, matrix-free algorithms for estimating matrix traces, log determinants, diagonals, and diagonals of inverses.
Author-email: Jonathan Lindbloom <jonathan@lindbloom.com>
Project-URL: Homepage, https://github.com/jlindbloom/randomized-trace-logdet-diag-diaginv
Project-URL: Bug Tracker, https://github.com/jlindbloom/randomized-trace-logdet-diag-diaginv/issues
Keywords: linear algebra,log determinant,trace,randomized estimators
Classifier: Programming Language :: Python :: 3
Classifier: License :: OSI Approved :: MIT License
Classifier: Operating System :: OS Independent
Classifier: Topic :: Scientific/Engineering :: Mathematics
Requires-Python: >=3.7
License-File: LICENSE
